{
  "_meta": {
    "source": "ooyyo.com EU-wide price aggregation",
    "currency": "HUF",
    "updated": "2026-06-10",
    "eur_huf_rate": 355.14,
    "countries_scanned": [
      "Germany",
      "France",
      "Italy",
      "Spain",
      "Netherlands",
      "Belgium",
      "Austria",
      "Poland"
    ],
    "max_per_model": 30,
    "total_listings": 150,
    "attempts": 30,
    "failures": 0
  },
  "brands": {
    "Skoda": {
      "Octavia": {
        "2015": {
          "min": 4787287,
          "avg": 4787287,
          "max": 4787287,
          "count": 1
        },
        "2017": {
          "min": 3547848,
          "avg": 4258128,
          "max": 4968408,
          "count": 2
        },
        "2019": {
          "min": 7083267,
          "avg": 7084155,
          "max": 7085043,
          "count": 2
        },
        "2020": {
          "min": 6587847,
          "avg": 8136257,
          "max": 10618686,
          "count": 8
        },
        "2021": {
          "min": 8118500,
          "avg": 8448780,
          "max": 8860743,
          "count": 4
        },
        "2022": {
          "min": 6566538,
          "avg": 7439591,
          "max": 8860743,
          "count": 6
        },
        "2023": {
          "min": 4968408,
          "avg": 6195417,
          "max": 7422426,
          "count": 2
        },
        "2024": {
          "min": 8697378,
          "avg": 9407658,
          "max": 10117938,
          "count": 2
        },
        "2025": {
          "min": 8874948,
          "avg": 9799496,
          "max": 10973826,
          "count": 3
        }
      },
      "Superb": {
        "2007": {
          "min": 425812,
          "avg": 1270631,
          "max": 2837568,
          "count": 6
        },
        "2008": {
          "min": 709924,
          "avg": 1504230,
          "max": 2127288,
          "count": 5
        },
        "2009": {
          "min": 2127288,
          "avg": 2127288,
          "max": 2127288,
          "count": 1
        },
        "2010": {
          "min": 1367289,
          "avg": 1804111,
          "max": 2127288,
          "count": 4
        },
        "2011": {
          "min": 2304858,
          "avg": 2304858,
          "max": 2304858,
          "count": 1
        },
        "2012": {
          "min": 1063644,
          "avg": 2310185,
          "max": 4226166,
          "count": 5
        },
        "2013": {
          "min": 1154205,
          "avg": 1640746,
          "max": 2127288,
          "count": 2
        },
        "2014": {
          "min": 994036,
          "avg": 1609849,
          "max": 2095326,
          "count": 3
        },
        "2015": {
          "min": 2485624,
          "avg": 2838634,
          "max": 3015138,
          "count": 3
        }
      }
    },
    "BMW": {
      "3-Series": {
        "1999": {
          "min": 4439250,
          "avg": 4439250,
          "max": 4439250,
          "count": 1
        },
        "2006": {
          "min": 4258128,
          "avg": 4258128,
          "max": 4258128,
          "count": 1
        },
        "2008": {
          "min": 3902988,
          "avg": 4346913,
          "max": 4790838,
          "count": 2
        },
        "2010": {
          "min": 6388968,
          "avg": 6388968,
          "max": 6388968,
          "count": 1
        },
        "2012": {
          "min": 5678688,
          "avg": 5678688,
          "max": 5678688,
          "count": 1
        },
        "2013": {
          "min": 3459063,
          "avg": 4857427,
          "max": 5501118,
          "count": 4
        },
        "2014": {
          "min": 4226166,
          "avg": 5041212,
          "max": 5856258,
          "count": 2
        },
        "2015": {
          "min": 4609717,
          "avg": 4730464,
          "max": 4968408,
          "count": 3
        },
        "2017": {
          "min": 7631958,
          "avg": 7631958,
          "max": 7631958,
          "count": 1
        },
        "2018": {
          "min": 8345434,
          "avg": 8345434,
          "max": 8345434,
          "count": 1
        },
        "2019": {
          "min": 8519808,
          "avg": 12250376,
          "max": 15980944,
          "count": 2
        },
        "2020": {
          "min": 10476274,
          "avg": 11267526,
          "max": 12058778,
          "count": 2
        },
        "2021": {
          "min": 11008984,
          "avg": 11936137,
          "max": 13452703,
          "count": 3
        },
        "2022": {
          "min": 9510649,
          "avg": 11077526,
          "max": 12781488,
          "count": 4
        },
        "2023": {
          "min": 12927096,
          "avg": 12927096,
          "max": 12927096,
          "count": 1
        },
        "2024": {
          "min": 14592702,
          "avg": 14592702,
          "max": 14592702,
          "count": 1
        }
      }
    },
    "Mercedes-Benz": {
      "A-Class": {
        "1991": {
          "min": 6921678,
          "avg": 6921678,
          "max": 6921678,
          "count": 1
        },
        "1993": {
          "min": 24682230,
          "avg": 24682230,
          "max": 24682230,
          "count": 1
        },
        "2007": {
          "min": 4790838,
          "avg": 5234763,
          "max": 5678688,
          "count": 2
        },
        "2009": {
          "min": 4581306,
          "avg": 4581306,
          "max": 4581306,
          "count": 1
        },
        "2011": {
          "min": 9585228,
          "avg": 9585228,
          "max": 9585228,
          "count": 1
        },
        "2012": {
          "min": 13459806,
          "avg": 15590646,
          "max": 17721486,
          "count": 2
        },
        "2013": {
          "min": 8874948,
          "avg": 9924387,
          "max": 10973826,
          "count": 2
        },
        "2014": {
          "min": 13139824,
          "avg": 18111607,
          "max": 23083389,
          "count": 2
        },
        "2015": {
          "min": 12071208,
          "avg": 12071208,
          "max": 12071208,
          "count": 1
        },
        "2016": {
          "min": 11716068,
          "avg": 23615034,
          "max": 35514000,
          "count": 2
        },
        "2017": {
          "min": 10650648,
          "avg": 10650648,
          "max": 10650648,
          "count": 1
        },
        "2018": {
          "min": 34800168,
          "avg": 34800168,
          "max": 34800168,
          "count": 1
        },
        "2019": {
          "min": 15267468,
          "avg": 35846055,
          "max": 56424643,
          "count": 2
        },
        "2020": {
          "min": 22089708,
          "avg": 22089708,
          "max": 22089708,
          "count": 1
        },
        "2021": {
          "min": 25907463,
          "avg": 27150453,
          "max": 28393443,
          "count": 2
        },
        "2022": {
          "min": 25889706,
          "avg": 25889706,
          "max": 25889706,
          "count": 1
        },
        "2023": {
          "min": 29653834,
          "avg": 34091486,
          "max": 44356986,
          "count": 4
        },
        "2025": {
          "min": 53199972,
          "avg": 53199972,
          "max": 53199972,
          "count": 1
        },
        "2026": {
          "min": 35474934,
          "avg": 35492691,
          "max": 35510448,
          "count": 2
        }
      },
      "C-Class": {
        "1999": {
          "min": 1242990,
          "avg": 1242990,
          "max": 1242990,
          "count": 1
        },
        "2008": {
          "min": 3192708,
          "avg": 3192708,
          "max": 3192708,
          "count": 1
        },
        "2012": {
          "min": 5323548,
          "avg": 5323548,
          "max": 5323548,
          "count": 1
        },
        "2014": {
          "min": 7777566,
          "avg": 7777566,
          "max": 7777566,
          "count": 1
        },
        "2015": {
          "min": 5842053,
          "avg": 9715564,
          "max": 19177204,
          "count": 4
        },
        "2016": {
          "min": 6030277,
          "avg": 10870835,
          "max": 14912328,
          "count": 4
        },
        "2017": {
          "min": 22725408,
          "avg": 22725408,
          "max": 22725408,
          "count": 1
        },
        "2018": {
          "min": 7276818,
          "avg": 8435758,
          "max": 9585228,
          "count": 3
        },
        "2019": {
          "min": 7970762,
          "avg": 9295008,
          "max": 12341115,
          "count": 5
        },
        "2020": {
          "min": 14553637,
          "avg": 14553637,
          "max": 14553637,
          "count": 1
        },
        "2021": {
          "min": 12781488,
          "avg": 12781488,
          "max": 12781488,
          "count": 1
        },
        "2022": {
          "min": 11169153,
          "avg": 13395880,
          "max": 15622608,
          "count": 2
        },
        "2024": {
          "min": 15181879,
          "avg": 19944573,
          "max": 32317740,
          "count": 4
        },
        "2025": {
          "min": 35471383,
          "avg": 35471383,
          "max": 35471383,
          "count": 1
        }
      }
    }
  }
}
